COPYRIGHT.txt
LICENSE.txt
bootstrap.py
buildout.cfg
setup.py
docs/HISTORY.txt
src/megrok/__init__.py
src/megrok.resourceviewlet.egg-info/PKG-INFO
src/megrok.resourceviewlet.egg-info/SOURCES.txt
src/megrok.resourceviewlet.egg-info/dependency_links.txt
src/megrok.resourceviewlet.egg-info/namespace_packages.txt
src/megrok.resourceviewlet.egg-info/not-zip-safe
src/megrok.resourceviewlet.egg-info/requires.txt
src/megrok.resourceviewlet.egg-info/top_level.txt
src/megrok/resourceviewlet/README.txt
src/megrok/resourceviewlet/__init__.py
src/megrok/resourceviewlet/components.py
src/megrok/resourceviewlet/ftests/__init__.py
src/megrok/resourceviewlet/ftests/ftesting.zcml
src/megrok/resourceviewlet/ftests/test_general.py
src/megrok/resourceviewlet/ftests/resources/thing.js