Metadata-Version: 1.0
Name: megrok.resourceviewlet
Version: 0.2
Summary: Grok components to include resources.
Home-page: http://pypi.python.org/pypi/megrok.resourceviewlet
Author: Souheil Chelfouh
Author-email: trollfot@gmail.com
License: ZPL 2.1
Download-URL: http://pypi.python.org/pypi/megrok.resourceviewlet
Keywords: Grok resources fanstatic
Platform: Any
Classifier: Development Status :: 4 - Beta
Classifier: Environment :: Web Environment
Classifier: Framework :: Zope3
Classifier: Intended Audience :: Other Audience
Classifier: License :: OSI Approved :: Zope Public License
Classifier: Operating System :: OS Independent
Classifier: Programming Language :: Python
